{
    "project_info": {
        "project_number": "34162146457",
        "project_id": "kn-ai-4d2e6",
        "storage_bucket": "kn-ai-4d2e6.firebasestorage.app"
    },
    "client": [
        {
            "client_info": {
                "mobilesdk_app_id": "1:34162146457:android:946c0b245883353c69cc08",
                "android_client_info": {
                    "package_name": "com.knstudio.ai"
                }
            },
            "oauth_client": [],
            "api_key": [
                {
                    "current_key": "AIzaSyCUa-5ak8UpKAbfi1YukQAXRcZuNzFMi30"
                }
            ],
            "services": {
                "appinvite_service": {
                    "other_platform_oauth_client": []
                }
            }
        }
    ],
    "configuration_version": "1"
}